neuroginius/__init__.py
neuroginius/atlas.py
neuroginius/decoding_pipeline.py
neuroginius/edge_ts.py
neuroginius/frame_selection.py
neuroginius/functional_connectivity.py
neuroginius/functional_decoding/__init__.py
neuroginius/functional_decoding/meta_analytic_decoding.py
neuroginius/iterables.py
neuroginius/matrices.py
neuroginius/models.py
neuroginius/networks.py
neuroginius/parcellate.py
neuroginius/plotting/__init__.py
neuroginius/plotting/chord_plot.py
neuroginius/plotting/fdr.py
neuroginius/plotting/matrix.py
neuroginius/synthetic_data/generation.py
neuroginius/wip/RegressionPredictors.py
neuroginius/wip/SQLInterface/RetrieveData.py
neuroginius/wip/SQLInterface/connectivity.py
neuroginius/wip/compute_networkfreqs.py
neuroginius/wip/retrieve_data.py
neuroginius/wip/retrieve_parcellated_data.py
neuroginius-0.1.1.dist-info/LICENSE
neuroginius-0.1.1.dist-info/METADATA
neuroginius-0.1.1.dist-info/WHEEL
neuroginius-0.1.1.dist-info/RECORD
