Metadata-Version: 2.1
Name: neuroginius
Version: 0.1.1
Summary: A repertoire of tools in python for high-level analyses of fMRI data.
Author: Achille Gillig
Author-email: achille.gillig@u-bordeaux.fr
Requires-Python: >3.10.0,<4.0
Classifier: License :: OSI Approved :: MIT License
Classifier: Operating System :: OS Independent
Classifier: Programming Language :: Python :: 3
Classifier: Programming Language :: Python :: 3.11
Classifier: Programming Language :: Python :: 3.12
Requires-Dist: brainsmash (>=0.11.0,<0.12.0)
Requires-Dist: matplotlib (>3.5.0)
Requires-Dist: nilearn (>0.10.0)
Requires-Dist: numpy (>1.20.0)
Requires-Dist: pandas (>2.0.0)
Requires-Dist: pycirclize (>=1.6.0,<2.0.0)
Requires-Dist: scikit-learn (>1.2.0)
Requires-Dist: scipy (>1.14.0)
Requires-Dist: seaborn (>0.13.0)
Requires-Dist: setuptools (>0.70.0)
